safeincave/Grid.py
safeincave/HeatBC.py
safeincave/HeatEquation.py
safeincave/MaterialProps.py
safeincave/MomentumBC.py
safeincave/MomentumEquation.py
safeincave/OutputHandler.py
safeincave/PostProcessingTools.py
safeincave/ScreenOutput.py
safeincave/Simulators.py
safeincave/TimeHandler.py
safeincave/Utils.py
safeincave/__init__.py
safeincave/app/MyBoundaryCond.py
safeincave/app/MyConstitutiveModel.py
safeincave/app/__init__.py
safeincave/app/gsapp.py
safeincave/app/script_runner.py
safeincave/app/sim_cli.py
safeincave/app/simulator_runner.py
safeincave/app/simulator_runner_backup.py
safeincave/app/simulator_runner_old.py
safeincave/app/assets/logo32.png
safeincave/app/assets/logo_2.png
safeincave/app/assets/logo_alone_2.png
safeincave-2.0.0.dist-info/licenses/LICENSE
safeincave-2.0.0.dist-info/METADATA
safeincave-2.0.0.dist-info/WHEEL
safeincave-2.0.0.dist-info/top_level.txt
safeincave-2.0.0.dist-info/RECORD
