Metadata-Version: 2.4
Name: safeincave
Version: 2.0.0
Summary: Simulator and tools for salt cavern stability and storage analyses
Author: Hermínio T. Honório
License: GPL-3.0-only
Project-URL: Repository, https://github.com/ADMIRE-Public/SafeInCave
Requires-Python: >=3.8
License-File: LICENSE
Requires-Dist: numpy==1.26.4
Requires-Dist: scipy==1.14.1
Requires-Dist: torch==2.4.0
Requires-Dist: meshio==3.3.1
Requires-Dist: gmsh>=4.14.0
Requires-Dist: lxml
Requires-Dist: pytz
Requires-Dist: h5py
Dynamic: license-file
